CHANGELOG.rst
LICENSE.txt
MANIFEST.in
README.rst
setup.cfg
setup.py
examples/__init__.py
examples/api_key.py
examples/api_key_delete.py
examples/api_key_report.py
examples/crf_extractor.py
examples/dashboard.py
examples/dashboard_export_models.py
examples/dashboard_import_models.py
examples/dashboard_vaporise_trashed.py
examples/data_object_del_all.py
examples/data_object_del_and_vaporise.py
examples/data_object_get_details.py
examples/data_object_list_fix.py
examples/data_object_list_interactions.py
examples/data_object_save_all.py
examples/date_parser.py
examples/duckling_extractor.py
examples/emotion_classifier.py
examples/faq_matcher.py
examples/faq_matcher_get_details.py
examples/faq_matcher_load_from_trash.py
examples/faq_matcher_load_training_samples_from_csv.py
examples/faq_matcher_retrieve.py
examples/faq_matcher_save_training_samples_to_csv.py
examples/faq_matcher_single_language.py
examples/health.py
examples/image_classifier.py
examples/image_classifier_vimba.py
examples/image_classifier_webcam.py
examples/image_reader.py
examples/intent_classifier.py
examples/intent_classifier_load_from_history.py
examples/intent_classifier_load_from_trash.py
examples/intent_classifier_load_training_samples_from_csv.py
examples/intent_classifier_retrieve.py
examples/intent_classifier_save_training_samples_to_csv.py
examples/intent_classifier_watson_workspace_import.py
examples/intent_flow_watson_workspace_import.py
examples/lr4_lang_ident.py
examples/pdf417_i.py
examples/pdf417_ii.py
examples/person_name_extractor.py
examples/regex_extractor.py
examples/sentiment_detector.py
examples/similarity_extractor.py
examples/similarity_extractor_tumi_workspace_import.py
examples/synonym_extractor.py
examples/synonym_extractor_test.py
examples/text_classifier.py
examples/text_classifier_fuzzy.py
examples/text_clsfr_load_from_trash.py
examples/word_manifold_modify.py
examples/word_manifold_use.py
feersum_nlu/__init__.py
feersum_nlu/api_client.py
feersum_nlu/configuration.py
feersum_nlu.egg-info/PKG-INFO
feersum_nlu.egg-info/SOURCES.txt
feersum_nlu.egg-info/dependency_links.txt
feersum_nlu.egg-info/requires.txt
feersum_nlu.egg-info/top_level.txt
