Metadata-Version: 1.1
Name: feersum-nlu
Version: 2.0.45.post4
Summary: FeersumNLU API
Home-page: https://github.com/praekelt/feersum-nlu-api-wrappers
Author: Feersum Engine
Author-email: nlu@feersum.io
License: UNKNOWN
Download-URL: https://github.com/praekelt/feersum-nlu-api-wrappers/archive/2.0.45.post4.tar.gz
Keywords: Feersum,NLU,NLP
Platform: UNKNOWN
